{
    "book_id": "చందమామ_1968_07",
    "stories": [
        {
            "title": "వీరగంగుడు (బేతాళకథ)",
            "page_start": 3,
            "author": "టి. యస్. వెంకటేశమూర్తి"
        },
        {
            "title": "కోళ్ళదొంగ",
            "page_start": 5,
            "author": "ఎస్. నిర్మల"
        },
        {
            "title": "కృష్ణావతారం",
            "page_start": 5,
            "author": "చందమామ బృందం"
        },
        {
            "title": "అరణ్యపురాణం",
            "page_start": 6,
            "author": "చందమామ బృందం"
        },
        {
            "title": "శిథిలాలయం",
            "page_start": 7,
            "author": "చందమామ బృందం"
        },
        {
            "title": "కూరగాయల తోట",
            "page_start": 22,
            "author": "కొంపల్లి బ్రహ్మానందరావు"
        },
        {
            "title": "లక్షలసమస్య",
            "page_start": 27,
            "author": "పి. నాగేంద్రరావు"
        },
        {
            "title": "ఓటమితో గెలుపు",
            "page_start": 30,
            "author": "ఆర్. సూర్యావతి"
        },
        {
            "title": "దోమ పులిరంగారావు",
            "page_start": 33,
            "author": "కె. వెంకట్రాజు"
        },
        {
            "title": "మాట పట్టింపు",
            "page_start": 36,
            "author": "బి. సత్యానందం"
        },
        {
            "title": "వేలిమీది గోరు",
            "page_start": 41,
            "author": "ఎన్. ఉదయశంకర్"
        },
        {
            "title": "కుంటికోతి",
            "page_start": 44,
            "author": "జె. కుమారస్వామి"
        },
        {
            "title": "రుజువు",
            "page_start": 47,
            "author": "సి. హెచ్. పి. నారాయణరావు"
        },
        {
            "title": "మృతనగరం సేంట్ పియర్ (ప్రపంచపు వింతలు)",
            "page_start": 61,
            "author": "చందమామ బృందం"
        },
        {
            "title": "టిప్పుసుల్తాను పతనర (భారత చరిత్ర)",
            "page_start": 82,
            "author": "చందమామ బృందం"
        }
    ]
}