{
    "book_id": "చందమామ_1966_12",
    "stories": [
        {
            "title": "భారతచరిత్ర - 63",
            "page_start": 2,
            "author": "చందమామ బృందం"
        },
        {
            "title": "నెహ్రూకథ",
            "page_start": 5,
            "author": "చందమామ బృందం"
        },
        {
            "title": "పాతాళదుర్గం - 8",
            "page_start": 9,
            "author": "చందమామ బృందం"
        },
        {
            "title": "దైవికదాంపత్యం",
            "page_start": 17,
            "author": "చందమామ బృందం"
        },
        {
            "title": "దురభిమానం",
            "page_start": 22,
            "author": "వి. రమణారావు"
        },
        {
            "title": "యక్షుడినవ్వులు",
            "page_start": 25,
            "author": "సి. సీతారామయ్య"
        },
        {
            "title": "వెర్రివెంకి",
            "page_start": 29,
            "author": "కె. శ్రీనివాసులు"
        },
        {
            "title": "పుత్రుడిక ర్తవ్యం",
            "page_start": 33,
            "author": "చందమామ బృందం"
        },
        {
            "title": "మనుష్యయత్నం",
            "page_start": 41,
            "author": "జె. రఘునాధరావు"
        },
        {
            "title": "పాతాళనాగు",
            "page_start": 44,
            "author": "ఎల్. అనంతయ్య"
        },
        {
            "title": "కృష్ణావతారం",
            "page_start": 49,
            "author": "చందమామ బృందం"
        },
        {
            "title": "అరణ్యపురాణం",
            "page_start": 57,
            "author": "చందమామ బృందం"
        }
    ]
}