{
    "book_id": "చందమామ_1957_03",
    "stories": [
        {
            "title": "దానపాత్రుడు (జా.క.)",
            "page_start": 4,
            "author": "చందమామ బృందం"
        },
        {
            "title": "ముగ్గురు మాంత్రికులు",
            "page_start": 9,
            "author": "చందమామ బృందం"
        },
        {
            "title": "ప్రాణంపొందిన ప్రతిమ",
            "page_start": 17,
            "author": "చందమామ బృందం"
        },
        {
            "title": "కుచుమారుడు",
            "page_start": 24,
            "author": "ఆర్. వెంకటాచారి"
        },
        {
            "title": "రంగన్న విశ్వాసం",
            "page_start": 33,
            "author": "పి. రాజలింగం"
        },
        {
            "title": "మిత్రభేదం (గేయకథ)",
            "page_start": 39,
            "author": "విద్వాన్ విశ్వం"
        },
        {
            "title": "నావికుడు సిందాబాద్",
            "page_start": 42,
            "author": "చందమామ బృందం"
        },
        {
            "title": "భువనసుందరి - 6",
            "page_start": 49,
            "author": "చందమామ బృందం"
        },
        {
            "title": "మూగనోము",
            "page_start": 57,
            "author": "ఆర్. మునిరామయ్య"
        },
        {
            "title": "రాబందు రభస",
            "page_start": 66,
            "author": "టి. శంభుదాసు"
        }
    ]
}