{
    "book_id": "చందమామ_2003_01",
    "stories": [
        {
            "title": "సుప్రసిద్ధం కాని సుందరప్రదేశాలు",
            "page_start": 10,
            "author": "చందమామ బృందం"
        },
        {
            "title": "అవ్వసాయం",
            "page_start": 11,
            "author": "జి. శ్రావ్యగీతా శైలజ"
        },
        {
            "title": "మాయాసరోవరం",
            "page_start": 12,
            "author": "చందమామ బృందం"
        },
        {
            "title": "వారసుడు (బే.క)",
            "page_start": 19,
            "author": "చందమామ బృందం"
        },
        {
            "title": "భారత దర్శిని",
            "page_start": 25,
            "author": "చందమామ బృందం"
        },
        {
            "title": "మేఘాలు ప్రేమించిన ముని కుమారుడు!",
            "page_start": 26,
            "author": "బిందుసార్"
        },
        {
            "title": "అతిశర్మ పొగడ్తలు",
            "page_start": 29,
            "author": "వసుంధర"
        },
        {
            "title": "చందమామ కబుర్లు",
            "page_start": 33,
            "author": "చందమామ బృందం"
        },
        {
            "title": "గుప్తదానం",
            "page_start": 34,
            "author": "గవ్వల నిర్మలాదేవి"
        },
        {
            "title": "గెలిపించిన విశ్వాసం!",
            "page_start": 37,
            "author": "చందమామ బృందం"
        },
        {
            "title": "లక్ష వరహాల సలహాలు (ఆంధ్ర ప్రదేశ్ జానపద కథ)",
            "page_start": 38,
            "author": "చందమామ బృందం"
        },
        {
            "title": "మనదేశం గురించి తెలుసు కుందాం",
            "page_start": 44,
            "author": "చందమామ బృందం"
        },
        {
            "title": "విఘ్నేశ్వరుడు",
            "page_start": 45,
            "author": "చందమామ బృందం"
        },
        {
            "title": "చిన్నయ్య దానగుణం",
            "page_start": 51,
            "author": "చందమామ బృందం"
        },
        {
            "title": "మిష్కిన్ అదృష్టం! (పర్షియాజానపద కథ)",
            "page_start": 52,
            "author": "చందమామ బృందం"
        },
        {
            "title": "ఏవి ఉత్తమమైనవి?",
            "page_start": 57,
            "author": "మంజుభారతి"
        },
        {
            "title": "అజేయుడు గరుడుడు!",
            "page_start": 60,
            "author": "చందమామ బృందం"
        },
        {
            "title": "వినోద సమయం",
            "page_start": 64,
            "author": "చందమామ బృందం"
        },
        {
            "title": "ఫొటో వ్యాఖ్యల పోటీ",
            "page_start": 66,
            "author": "చందమామ బృందం"
        }
    ]
}