{
    "book_id": "చందమామ_2003_09",
    "stories": [
        {
            "title": "దళాధిపతి అభిప్రాయం",
            "page_start": 8,
            "author": "చందమామ బృందం"
        },
        {
            "title": "మంచితనపు మహత్తు",
            "page_start": 9,
            "author": "లక్ష్మీగాయత్రి"
        },
        {
            "title": "మాయాసరోవరం",
            "page_start": 13,
            "author": "చందమామ బృందం"
        },
        {
            "title": "ధైర్యవంతుడు",
            "page_start": 19,
            "author": "చందమామ బృందం"
        },
        {
            "title": "భారతదర్శిని",
            "page_start": 26,
            "author": "చందమామ బృందం"
        },
        {
            "title": "సన్యాసి-పండు",
            "page_start": 27,
            "author": "బిందుసార్"
        },
        {
            "title": "వ్యర్థమైన వరాలు",
            "page_start": 30,
            "author": "కొనే నాగవెంకట ఆంజనేయులు"
        },
        {
            "title": "మంత్రగత్తె - అందమైన అమ్మాయిలు",
            "page_start": 34,
            "author": "చందమామ బృందం"
        },
        {
            "title": "చందమామ కబుర్లు",
            "page_start": 39,
            "author": "చందమామ బృందం"
        },
        {
            "title": "గురుదక్షిణ",
            "page_start": 40,
            "author": "డా. జొన్నలగడ్డ మార్కండేయులు"
        },
        {
            "title": "మనదేశం గురించి తెలుసుకుందాం",
            "page_start": 44,
            "author": "చందమామ బృందం"
        },
        {
            "title": "విఘ్నేశ్వరుడు",
            "page_start": 45,
            "author": "చందమామ బృందం"
        },
        {
            "title": "గోవిందుడి తపస్సు",
            "page_start": 51,
            "author": "లలిత-శర్మిళ"
        },
        {
            "title": "కథలు చెప్పేవాడు",
            "page_start": 55,
            "author": "ఎన్. శివనాగేశ్వరరావు"
        },
        {
            "title": "జల పరిరక్షణ",
            "page_start": 58,
            "author": "చందమామ బృందం"
        },
        {
            "title": "ఆర్య",
            "page_start": 60,
            "author": "చందమామ బృందం"
        },
        {
            "title": "వినోద సమయం",
            "page_start": 64,
            "author": "చందమామ బృందం"
        },
        {
            "title": "ఫొటో వ్యాఖ్యల పోటీ",
            "page_start": 66,
            "author": "చందమామ బృందం"
        }
    ]
}